{
  "project_info": {
    "project_number": "812214112429",
    "project_id": "condeapp-5016e",
    "storage_bucket": "condeapp-5016e.appspot.com"
  },
  "client": [
    {
      "client_info": {
        "mobilesdk_app_id": "1:812214112429:android:ba92b5ad4b7749c43f3624",
        "android_client_info": {
          "package_name": "com.example.condeapp"
        }
      },
      "oauth_client": [
        {
          "client_id": "812214112429-fbomlnucfkuhebh2id3lfsc3pvvcrb36.apps.googleusercontent.com",
          "client_type": 3
        }
      ],
      "api_key": [
        {
          "current_key": "AIzaSyBhm5U6-EBykjfWkkLu4-sgtuBXSOsareo"
        }
      ],
      "services": {
        "appinvite_service": {
          "other_platform_oauth_client": [
            {
              "client_id": "812214112429-fbomlnucfkuhebh2id3lfsc3pvvcrb36.apps.googleusercontent.com",
              "client_type": 3
            }
          ]
        }
      }
    }
  ],
  "configuration_version": "1"
}